arawinz_sdk_test/__init__.py
arawinz_s_sdk-0.0.11.dist-info/METADATA
arawinz_s_sdk-0.0.11.dist-info/WHEEL
arawinz_s_sdk-0.0.11.dist-info/top_level.txt
arawinz_s_sdk-0.0.11.dist-info/RECORD
