Metadata-Version: 2.1
Name: arawinz-s-sdk
Version: 0.0.11
Summary: sample SDK by Arawinz
Home-page: UNKNOWN
Author: Arawinz (Chethan Pasupuleti)
Author-email: <chethanpss24@gmail.com>
License: UNKNOWN
Keywords: python,arawinz,algorand,sdk
Platform: UNKNOWN
Classifier: Development Status :: 1 - Planning
Classifier: Intended Audience :: Developers
Classifier: Programming Language :: Python :: 3
Classifier: Operating System :: Unix
Classifier: Operating System :: MacOS :: MacOS X
Classifier: Operating System :: Microsoft :: Windows
Requires-Dist: requests
Requires-Dist: py-algorand-sdk
Requires-Dist: pytz
